prompt_autotune/Evaluation.py
prompt_autotune/GenerateExamples.py
prompt_autotune/PROMPTS.py
prompt_autotune/TunePrompt.py
prompt_autotune/__init__.py
prompt_autotune/main.py
prompt_autotune-0.4.0.dist-info/LICENSE
prompt_autotune-0.4.0.dist-info/METADATA
prompt_autotune-0.4.0.dist-info/WHEEL
prompt_autotune-0.4.0.dist-info/entry_points.txt
prompt_autotune-0.4.0.dist-info/top_level.txt
prompt_autotune-0.4.0.dist-info/RECORD
