Metadata-Version: 2.1
Name: prompt_autotune
Version: 0.4.0
Summary: A light weight library that takes in a `task description` and a `prompt` and tunes the prompt to perform better.
Home-page: https://github.com/ChinmayShrivastava/prompt-autotune
Author: Chinmay Shrivastava
Author-email: cshrivastava99@gmail.com
License: MIT
Classifier: Programming Language :: Python :: 3
Classifier: License :: OSI Approved :: MIT License
Classifier: Operating System :: OS Independent
License-File: LICENSE
Requires-Dist: llama-index ==0.10.20
Requires-Dist: python-dotenv
